langchain_zeusdb/__init__.py
langchain_zeusdb/py.typed
langchain_zeusdb/vectorstores.py
langchain_zeusdb-0.1.1.dist-info/METADATA
langchain_zeusdb-0.1.1.dist-info/WHEEL
langchain_zeusdb-0.1.1.dist-info/licenses/LICENSE
langchain_zeusdb-0.1.1.dist-info/RECORD
