Metadata-Version: 2.4
Name: langchain-zeusdb
Version: 0.1.1
Summary: An integration package connecting ZeusDB and LangChain.
Project-URL: Homepage, https://github.com/zeusdb/langchain-zeusdb
Project-URL: Repository, https://github.com/zeusdb/langchain-zeusdb
Project-URL: Documentation, https://docs.zeusdb.com
Project-URL: Bug Tracker, https://github.com/zeusdb/langchain-zeusdb/issues
Author-email: ZeusDB <contact@zeusdb.com>
License: MIT License
License-File: LICENSE
Classifier: License :: OSI Approved :: MIT License
Classifier: Operating System :: OS Independent
Classifier: Programming Language :: Python :: 3
Classifier: Programming Language :: Python :: 3.10
Classifier: Programming Language :: Python :: 3.11
Classifier: Programming Language :: Python :: 3.12
Classifier: Programming Language :: Python :: 3.13
Requires-Python: >=3.10
Requires-Dist: langchain-core<0.4,>=0.3.74
Requires-Dist: zeusdb>=0.0.8
